datacentric/__init__.py
datacentric-2.1.0.dist-info/LICENSE
datacentric-2.1.0.dist-info/METADATA
datacentric-2.1.0.dist-info/WHEEL
datacentric-2.1.0.dist-info/top_level.txt
datacentric-2.1.0.dist-info/RECORD
