Metadata-Version: 2.1
Name: datacentric
Version: 2.1.0
Summary: Core services library for data-centric development.
Home-page: https://github.com/datacentricorg/datacentric-py
Author: The DataCentric Authors
Author-email: sokol@dualitygroup.com
License: UNKNOWN
Platform: UNKNOWN
Classifier: Programming Language :: Python :: 3
Classifier: License :: OSI Approved :: Apache Software License
Classifier: Operating System :: OS Independent
